{
  "db_name": "PostgreSQL",
  "query": "\n            SELECT\n                id              AS \"id: MentionId\",\n                prompt_run_id   AS \"prompt_run_id: PromptRunId\",\n                entity,\n                char_offset,\n                rank,\n                matched_text,\n                organization_id,\n                tenant_id,\n                created_at\n            FROM mentions\n            WHERE id = $1\n            ",
  "describe": {
    "columns": [
      {
        "ordinal": 0,
        "name": "id: MentionId",
        "type_info": "Uuid"
      },
      {
        "ordinal": 1,
        "name": "prompt_run_id: PromptRunId",
        "type_info": "Uuid"
      },
      {
        "ordinal": 2,
        "name": "entity",
        "type_info": "Text"
      },
      {
        "ordinal": 3,
        "name": "char_offset",
        "type_info": "Int4"
      },
      {
        "ordinal": 4,
        "name": "rank",
        "type_info": "Int4"
      },
      {
        "ordinal": 5,
        "name": "matched_text",
        "type_info": "Text"
      },
      {
        "ordinal": 6,
        "name": "organization_id",
        "type_info": "Uuid"
      },
      {
        "ordinal": 7,
        "name": "tenant_id",
        "type_info": "Uuid"
      },
      {
        "ordinal": 8,
        "name": "created_at",
        "type_info": "Timestamptz"
      }
    ],
    "parameters": {
      "Left": [
        "Uuid"
      ]
    },
    "nullable": [
      false,
      false,
      false,
      false,
      false,
      false,
      true,
      true,
      false
    ]
  },
  "hash": "a93c89b98af283c9db7734a33b62eb3311cabc28fcd07e7ef551929585ec68ab"
}
